{"composer_id": "composer_3354", "composer_url": "https://www.classicalarchives.com/midi/composer/3354.html", "info": "(ca. 1630-1705); HRV", "name": "Ivan Sibencanin", "ntrack": 1, "nwork": 1, "work_list": [{"npage": 1, "ntrack": 1, "page_list": [{"contributor": "Trpimir Matasovic", "contributor_url": "https://www.classicalarchives.com/contributor/1135.html", "length": "5:16", "ntrack": 1, "page_id": "page_1", "track_list": [{"length": "5:16", "title": "Lauda Jerusalem Dominum", "track_id": "track_1"}]}], "title": "Lauda Jerusalem Dominum", "work_id": "work_26419"}]}
