{"composer_id": "composer_3210", "composer_url": "https://www.classicalarchives.com/midi/composer/3210.html", "info": "(1875-1937); FRA", "name": "Maurice Ravel", "ntrack": 88, "nwork": 20, "work_list": [{"npage": 1, "ntrack": 1, "page_list": [{"contributor": "Mika Haveri", "contributor_url": "https://www.classicalarchives.com/contributor/731.html", "length": "16:27", "ntrack": 1, "page_id": "page_1", "track_list": [{"length": "16:27", "title": "Bol\u00e9ro (ballet)", "track_id": "track_1"}]}], "title": "Bol\u00e9ro (ballet)", "work_id": "work_144521"}, {"npage": 4, "ntrack": 13, "page_list": [{"contributor": "Jack Sirulnikoff", "contributor_url": "https://www.classicalarchives.com/contributor/1679.html", "length": "3:48", "ntrack": 1, "page_id": "page_1", "track_list": [{"length": "3:48", "title": "5.Les entretiens de la Belle et de la Bete", "track_id": "track_1"}]}, {"contributor": "Jof Lee", "contributor_url": "https://www.classicalarchives.com/contributor/996.html", "length": "8:40", "ntrack": 3, "page_id": "page_2", "track_list": [{"length": "1:28", "title": "3.Pavane de la Belle au Bois dormant", "track_id": "track_1"}, {"length": "4:04", "title": "5.Les entretiens de la Belle et de la Bete", "track_id": "track_2"}, {"length": "3:08", "title": "11.Le jardin f\u00e9erique", "track_id": "track_3"}]}, {"contributor": "Chiaki Ikenoue", "contributor_url": "https://www.classicalarchives.com/contributor/810.html", "length": "13:25", "ntrack": 4, "page_id": "page_3", "track_list": [{"length": "1:46", "title": "3.Pavane de la Belle au Bois dormant", "track_id": "track_1"}, {"length": "3:50", "title": "7.Petit Poucet", "track_id": "track_2"}, {"length": "3:44", "title": "9.Laideronnette, Imperatrice des Pagodes", "track_id": "track_3"}, {"length": "4:05", "title": "11.Le jardin f\u00e9erique", "track_id": "track_4"}]}, {"contributor": "Jack Sirulnikoff", "contributor_url": "https://www.classicalarchives.com/contributor/1679.html", "length": "14:50", "ntrack": 5, "page_id": "page_4", "track_list": [{"length": "1:21", "title": "3.Pavane de la Belle au Bois dormant", "track_id": "track_1"}, {"length": "3:37", "title": "5.Les entretiens de la Belle et de la Bete", "track_id": "track_2"}, {"length": "3:20", "title": "7.Petit Poucet", "track_id": "track_3"}, {"length": "3:25", "title": "9.Laideronnette, Imperatrice des Pagodes", "track_id": "track_4"}, {"length": "3:07", "title": "11.Le jardin f\u00e9erique", "track_id": "track_5"}]}], "title": "Ma m\u00e8re l'oye (ballet)", "work_id": "work_107388"}, {"npage": 3, "ntrack": 4, "page_list": [{"contributor": "Robert S. Finley", "contributor_url": "https://www.classicalarchives.com/contributor/3955.html", "length": "5:41", "ntrack": 1, "page_id": "page_1", "track_list": [{"length": "5:41", "title": "1.Ondine", "track_id": "track_1"}]}, {"contributor": "Frank Lin", "contributor_url": "https://www.classicalarchives.com/contributor/1020.html", "length": "9:13", "ntrack": 1, "page_id": "page_2", "track_list": [{"length": "9:13", "title": "3.Scarbo", "track_id": "track_1"}]}, {"contributor": "Peter R. Wolfe", "contributor_url": "https://www.classicalarchives.com/contributor/1979.html", "length": "13:39", "ntrack": 2, "page_id": "page_3", "track_list": [{"length": "5:29", "title": "2.Le gibet", "track_id": "track_1"}, {"length": "8:10", "title": "3.Scarbo", "track_id": "track_2"}]}], "title": "Gaspard de la nuit", "work_id": "work_22766"}, {"npage": 4, "ntrack": 4, "page_list": [{"contributor": "Jack Sirulnikoff", "contributor_url": "https://www.classicalarchives.com/contributor/1679.html", "length": "4:40", "ntrack": 1, "page_id": "page_1", "track_list": [{"length": "4:40", "title": "Jeux d'eau, for piano", "track_id": "track_1"}]}, {"contributor": "Tatsuya Tanaka", "contributor_url": "https://www.classicalarchives.com/contributor/1780.html", "length": "5:25", "ntrack": 1, "page_id": "page_2", "track_list": [{"length": "5:25", "title": "Jeux d'eau, for piano", "track_id": "track_1"}]}, {"contributor": "Daniel Mateos Moreno", "contributor_url": "https://www.classicalarchives.com/contributor/1136.html", "length": "5:33", "ntrack": 1, "page_id": "page_3", "track_list": [{"length": "5:33", "title": "Jeux d'eau, for piano", "track_id": "track_1"}]}, {"contributor": "John Cowles", "contributor_url": "https://www.classicalarchives.com/contributor/349.html", "length": "4:53", "ntrack": 1, "page_id": "page_4", "track_list": [{"length": "4:53", "title": "Jeux d'eau, for piano", "track_id": "track_1"}]}], "title": "Jeux d'eau, for piano", "work_id": "work_22771"}, {"npage": 6, "ntrack": 11, "page_list": [{"contributor": "Reinhold Behringer", "contributor_url": "https://www.classicalarchives.com/contributor/116.html", "length": "3:06", "ntrack": 1, "page_id": "page_1", "track_list": [{"length": "3:06", "title": "1.Pr\u00e9lude", "track_id": "track_1"}]}, {"contributor": "Sherri Hill", "contributor_url": "https://www.classicalarchives.com/contributor/764.html", "length": "5:28", "ntrack": 1, "page_id": "page_2", "track_list": [{"length": "5:28", "title": "3.Forlane", "track_id": "track_1"}]}, {"contributor": "Ram\u00f3n Pajares Box", "contributor_url": "https://www.classicalarchives.com/contributor/1338.html", "length": "4:27", "ntrack": 1, "page_id": "page_3", "track_list": [{"length": "4:27", "title": "5.Menuet", "track_id": "track_1"}]}, {"contributor": "Ram\u00f3n Pajares Box", "contributor_url": "https://www.classicalarchives.com/contributor/1338.html", "length": "4:32", "ntrack": 1, "page_id": "page_4", "track_list": [{"length": "4:32", "title": "5.Menuet ((arr.orch.))", "track_id": "track_1"}]}, {"contributor": "Lyndon J. Meyer", "contributor_url": "https://www.classicalarchives.com/contributor/1182.html", "length": "3:35", "ntrack": 1, "page_id": "page_5", "track_list": [{"length": "3:35", "title": "6.Toccata", "track_id": "track_1"}]}, {"contributor": "Robert Ungar", "contributor_url": "https://www.classicalarchives.com/contributor/1850.html", "length": "23:43", "ntrack": 6, "page_id": "page_6", "track_list": [{"length": "3:03", "title": "1.Pr\u00e9lude", "track_id": "track_1"}, {"length": "3:27", "title": "2.Fugue", "track_id": "track_2"}, {"length": "5:32", "title": "3.Forlane", "track_id": "track_3"}, {"length": "3:16", "title": "4.Rigaudon", "track_id": "track_4"}, {"length": "4:46", "title": "5.Menuet", "track_id": "track_5"}, {"length": "3:39", "title": "6.Toccata", "track_id": "track_6"}]}], "title": "Le tombeau de Couperin", "work_id": "work_22773"}, {"npage": 2, "ntrack": 6, "page_list": [{"contributor": "Peter R. Wolfe", "contributor_url": "https://www.classicalarchives.com/contributor/1979.html", "length": "6:19", "ntrack": 1, "page_id": "page_1", "track_list": [{"length": "6:19", "title": "4.Alborada del gracioso", "track_id": "track_1"}]}, {"contributor": "Jack Sirulnikoff", "contributor_url": "https://www.classicalarchives.com/contributor/1679.html", "length": "23:57", "ntrack": 5, "page_id": "page_2", "track_list": [{"length": "4:27", "title": "1.Noctuelles", "track_id": "track_1"}, {"length": "2:35", "title": "2.Oiseaux tristes", "track_id": "track_2"}, {"length": "7:39", "title": "3.Une barque sur l'ocean", "track_id": "track_3"}, {"length": "5:50", "title": "4.Alborada del gracioso", "track_id": "track_4"}, {"length": "3:26", "title": "5.La vall\u00e9e des cloches", "track_id": "track_5"}]}], "title": "Miroirs", "work_id": "work_22789"}, {"npage": 8, "ntrack": 8, "page_list": [{"contributor": "M. Anthony Deocariza", "contributor_url": "https://www.classicalarchives.com/contributor/428.html", "length": "5:41", "ntrack": 1, "page_id": "page_1", "track_list": [{"length": "5:41", "title": "Pavane pour une infante d\u00e9funte", "track_id": "track_1"}]}, {"contributor": "Chiaki Ikenoue", "contributor_url": "https://www.classicalarchives.com/contributor/810.html", "length": "6:37", "ntrack": 1, "page_id": "page_2", "track_list": [{"length": "6:37", "title": "Pavane pour une infante d\u00e9funte", "track_id": "track_1"}]}, {"contributor": "Ikuo Naoi", "contributor_url": "https://www.classicalarchives.com/contributor/1260.html", "length": "5:29", "ntrack": 1, "page_id": "page_3", "track_list": [{"length": "5:29", "title": "Pavane pour une infante d\u00e9funte (arr. orchestra)", "track_id": "track_1"}]}, {"contributor": "Nick H. Carter", "contributor_url": "https://www.classicalarchives.com/contributor/264.html", "length": "5:21", "ntrack": 1, "page_id": "page_4", "track_list": [{"length": "5:21", "title": "Pavane pour une infante d\u00e9funte ((piano arr.))", "track_id": "track_1"}]}, {"contributor": "Jack Sirulnikoff", "contributor_url": "https://www.classicalarchives.com/contributor/1679.html", "length": "5:40", "ntrack": 1, "page_id": "page_5", "track_list": [{"length": "5:40", "title": "Pavane pour une infante d\u00e9funte ((arr.orch.))", "track_id": "track_1"}]}, {"contributor": "Reinhold Behringer", "contributor_url": "https://www.classicalarchives.com/contributor/116.html", "length": "5:18", "ntrack": 1, "page_id": "page_6", "track_list": [{"length": "5:18", "title": "Pavane pour une infante d\u00e9funte", "track_id": "track_1"}]}, {"contributor": "Tom\u00e1s O\u2019Drisceoil", "contributor_url": "https://www.classicalarchives.com/contributor/1301.html", "length": "5:13", "ntrack": 1, "page_id": "page_7", "track_list": [{"length": "5:13", "title": "Pavane pour une infante d\u00e9funte", "track_id": "track_1"}]}, {"contributor": "Robert S. Finley", "contributor_url": "https://www.classicalarchives.com/contributor/3955.html", "length": "4:25", "ntrack": 1, "page_id": "page_8", "track_list": [{"length": "4:25", "title": "Pavane pour une infante d\u00e9funte", "track_id": "track_1"}]}], "title": "Pavane pour une infante d\u00e9funte", "work_id": "work_22797"}, {"npage": 1, "ntrack": 1, "page_list": [{"contributor": "Chris R. Jusell", "contributor_url": "https://www.classicalarchives.com/contributor/860.html", "length": "1:35", "ntrack": 1, "page_id": "page_1", "track_list": [{"length": "1:35", "title": "Pr\u00e9lude", "track_id": "track_1"}]}], "title": "Pr\u00e9lude", "work_id": "work_22799"}, {"npage": 2, "ntrack": 4, "page_list": [{"contributor": "Minoru Kawamura", "contributor_url": "https://www.classicalarchives.com/contributor/880.html", "length": "10:35", "ntrack": 3, "page_id": "page_1", "track_list": [{"length": "4:02", "title": "1.Mod\u00e9r\u00e9", "track_id": "track_1"}, {"length": "2:50", "title": "2.Mouvement de Menuet", "track_id": "track_2"}, {"length": "3:43", "title": "3.Anim\u00e9", "track_id": "track_3"}]}, {"contributor": "Jeffrey S. Covey", "contributor_url": "https://www.classicalarchives.com/contributor/347.html", "length": "3:01", "ntrack": 1, "page_id": "page_2", "track_list": [{"length": "3:01", "title": "2.Mouvement de Menuet ((arr.guitar trio))", "track_id": "track_1"}]}], "title": "Sonatine in F#-", "work_id": "work_22800"}, {"npage": 1, "ntrack": 2, "page_list": [{"contributor": "Lyndon J. Meyer", "contributor_url": "https://www.classicalarchives.com/contributor/1182.html", "length": "3:26", "ntrack": 2, "page_id": "page_1", "track_list": [{"length": "1:22", "title": "1.Mod\u00e9r\u00e9", "track_id": "track_1"}, {"length": "2:04", "title": "2.Assez lent", "track_id": "track_2"}]}], "title": "8 Valses nobles et sentimentales", "work_id": "work_22804"}, {"npage": 1, "ntrack": 1, "page_list": [{"contributor": "Yoshi Motokado", "contributor_url": "https://www.classicalarchives.com/contributor/1231.html", "length": "11:54", "ntrack": 1, "page_id": "page_1", "track_list": [{"length": "11:54", "title": "La valse (po\u00e8me chor\u00e9ographique), for 2 pianos (after orchestral work) ((for two pianos))", "track_id": "track_1"}]}], "title": "La valse (po\u00e8me chor\u00e9ographique), for 2 pianos (after orchestral work)", "work_id": "work_55959"}, {"npage": 2, "ntrack": 6, "page_list": [{"contributor": "Simon Scheiwiller", "contributor_url": "https://www.classicalarchives.com/contributor/1586.html", "length": "13:52", "ntrack": 5, "page_id": "page_1", "track_list": [{"length": "1:26", "title": "1.Pavane de la Belle au Bois dormant (Pavane of the Sleeping Beauty)", "track_id": "track_1"}, {"length": "2:44", "title": "2.Petit Poucet (Tom Thumb)", "track_id": "track_2"}, {"length": "3:21", "title": "3.Laideronnette, Imperatrice des Pagodes ('Little Ugly', Empress of the Pagodas)", "track_id": "track_3"}, {"length": "3:25", "title": "4.Les entretiens de la Belle et de la B\u00eate (The conversations of Beauty and the Beast)", "track_id": "track_4"}, {"length": "2:56", "title": "5.Le jardin f\u00e9erique (The fairy garden)", "track_id": "track_5"}]}, {"contributor": "David E. Lovell", "contributor_url": "https://www.classicalarchives.com/contributor/1052.html", "length": "0:57", "ntrack": 1, "page_id": "page_2", "track_list": [{"length": "0:57", "title": "1.Pavane de la Belle au Bois dormant (Pavane of the Sleeping Beauty) ((arr.gtr.))", "track_id": "track_1"}]}], "title": "Ma M\u00e8re l'Oye, for piano 4-hands", "work_id": "work_22780"}, {"npage": 3, "ntrack": 5, "page_list": [{"contributor": "Lyndon J. Meyer", "contributor_url": "https://www.classicalarchives.com/contributor/1182.html", "length": "7:44", "ntrack": 1, "page_id": "page_1", "track_list": [{"length": "7:44", "title": "1.Allegramente", "track_id": "track_1"}]}, {"contributor": "Christophe Koclejda", "contributor_url": "https://www.classicalarchives.com/contributor/927.html", "length": "21:06", "ntrack": 3, "page_id": "page_2", "track_list": [{"length": "8:50", "title": "1.Allegramente", "track_id": "track_1"}, {"length": "8:10", "title": "2.Adagio assai", "track_id": "track_2"}, {"length": "4:06", "title": "3.Presto", "track_id": "track_3"}]}, {"contributor": "Pietro Cecchi", "contributor_url": "https://www.classicalarchives.com/contributor/279.html", "length": "10:01", "ntrack": 1, "page_id": "page_3", "track_list": [{"length": "10:01", "title": "2.Adagio assai ((arr.))", "track_id": "track_1"}]}], "title": "Piano Concerto in G", "work_id": "work_22882"}, {"npage": 3, "ntrack": 6, "page_list": [{"contributor": "Warren Pepperdine", "contributor_url": "https://www.classicalarchives.com/contributor/1368.html", "length": "13:49", "ntrack": 1, "page_id": "page_1", "track_list": [{"length": "13:49", "title": "Rhapsodie espagnole ((arr.2p. by Ravel))", "track_id": "track_1"}]}, {"contributor": "Segundo G. Yogore", "contributor_url": "https://www.classicalarchives.com/contributor/1994.html", "length": "15:14", "ntrack": 4, "page_id": "page_2", "track_list": [{"length": "4:37", "title": "1.Pr\u00e9lude \u00e0 la nuit", "track_id": "track_1"}, {"length": "1:49", "title": "2.Malague\u00f1a", "track_id": "track_2"}, {"length": "2:41", "title": "3.Haba\u00f1era", "track_id": "track_3"}, {"length": "6:07", "title": "4.Feria", "track_id": "track_4"}]}, {"contributor": "Segundo G. Yogore", "contributor_url": "https://www.classicalarchives.com/contributor/1994.html", "length": "5:03", "ntrack": 1, "page_id": "page_3", "track_list": [{"length": "5:03", "title": "4.Feria ((arr.2p. by Ravel))", "track_id": "track_1"}]}], "title": "Rhapsodie espagnole", "work_id": "work_43960"}, {"npage": 1, "ntrack": 8, "page_list": [{"contributor": "Jack Sirulnikoff", "contributor_url": "https://www.classicalarchives.com/contributor/1679.html", "length": "13:51", "ntrack": 8, "page_id": "page_1", "track_list": [{"length": "1:13", "title": "1.Mod\u00e9r\u00e9", "track_id": "track_1"}, {"length": "1:55", "title": "2.Assez lent", "track_id": "track_2"}, {"length": "1:35", "title": "3.Mod\u00e9r\u00e9", "track_id": "track_3"}, {"length": "1:34", "title": "4.Assez anim\u00e9", "track_id": "track_4"}, {"length": "0:57", "title": "5.Presque lent", "track_id": "track_5"}, {"length": "0:47", "title": "6.Assez vif", "track_id": "track_6"}, {"length": "2:49", "title": "7.Moins vif", "track_id": "track_7"}, {"length": "3:01", "title": "8.\u00c9pilogue: Lent", "track_id": "track_8"}]}], "title": "Valses nobles et sentimentales (after piano work)", "work_id": "work_22829"}, {"npage": 1, "ntrack": 1, "page_list": [{"contributor": "David Siu", "contributor_url": "https://www.classicalarchives.com/contributor/1680.html", "length": "10:03", "ntrack": 1, "page_id": "page_1", "track_list": [{"length": "10:03", "title": "Introduction et Allegro, for flute, harp, clarinet, and string quartet", "track_id": "track_1"}]}], "title": "Introduction et Allegro, for flute, harp, clarinet, and string quartet", "work_id": "work_22838"}, {"npage": 1, "ntrack": 4, "page_list": [{"contributor": "Gregory Richardson", "contributor_url": "https://www.classicalarchives.com/contributor/1488.html", "length": "24:27", "ntrack": 4, "page_id": "page_1", "track_list": [{"length": "6:50", "title": "1.Allegro moderato. Tr\u00e8s doux", "track_id": "track_1"}, {"length": "6:00", "title": "2.Assez vif. Tr\u00e8s rythm\u00e9", "track_id": "track_2"}, {"length": "7:33", "title": "3.Tres lent", "track_id": "track_3"}, {"length": "4:04", "title": "4.Vif et agite", "track_id": "track_4"}]}], "title": "String Quartet in F", "work_id": "work_22844"}, {"npage": 1, "ntrack": 1, "page_list": [{"contributor": "David E. Lovell", "contributor_url": "https://www.classicalarchives.com/contributor/1052.html", "length": "1:06", "ntrack": 1, "page_id": "page_1", "track_list": [{"length": "1:06", "title": "Vocalise: \u00c9tude en forme de habanera (song) ((tr.gtr.))", "track_id": "track_1"}]}], "title": "Vocalise: \u00c9tude en forme de habanera (song)", "work_id": "work_22851"}, {"npage": 1, "ntrack": 1, "page_list": [{"contributor": "Simon Mokkie", "contributor_url": "https://www.classicalarchives.com/contributor/1209.html", "length": "2:40", "ntrack": 1, "page_id": "page_1", "track_list": [{"length": "2:40", "title": "1.Chanson espagnole", "track_id": "track_1"}]}], "title": "Chants populaires (song cycle), for voice and piano", "work_id": "work_150176"}, {"npage": 1, "ntrack": 1, "page_list": [{"contributor": "Eric J. Miller", "contributor_url": "https://www.classicalarchives.com/contributor/1194.html", "length": "1:30", "ntrack": 1, "page_id": "page_1", "track_list": [{"length": "1:30", "title": "1.Nicolette", "track_id": "track_1"}]}], "title": "3 Chansons, for a cappella chorus", "work_id": "work_22864"}]}
