{"composer_id": "composer_2743", "composer_url": "https://www.classicalarchives.com/midi/composer/2743.html", "info": "(1837-1879); DEU", "name": "Adolf Jensen", "ntrack": 18, "nwork": 7, "work_list": [{"npage": 1, "ntrack": 1, "page_list": [{"contributor": "Jos van Roy", "contributor_url": "https://www.classicalarchives.com/contributor/1869.html", "length": "2:26", "ntrack": 1, "page_id": "page_1", "track_list": [{"length": "2:26", "title": "Barcarolle", "track_id": "track_1"}]}], "title": "Barcarolle", "work_id": "work_14127"}, {"npage": 1, "ntrack": 1, "page_list": [{"contributor": "Jos van Roy", "contributor_url": "https://www.classicalarchives.com/contributor/1869.html", "length": "2:30", "ntrack": 1, "page_id": "page_1", "track_list": [{"length": "2:30", "title": "Canzonetta", "track_id": "track_1"}]}], "title": "Canzonetta", "work_id": "work_14128"}, {"npage": 1, "ntrack": 1, "page_list": [{"contributor": "Jos van Roy", "contributor_url": "https://www.classicalarchives.com/contributor/1869.html", "length": "2:24", "ntrack": 1, "page_id": "page_1", "track_list": [{"length": "2:24", "title": "Danse Antique Allemande", "track_id": "track_1"}]}], "title": "Danse Antique Allemande", "work_id": "work_14129"}, {"npage": 1, "ntrack": 1, "page_list": [{"contributor": "Jos van Roy", "contributor_url": "https://www.classicalarchives.com/contributor/1869.html", "length": "3:13", "ntrack": 1, "page_id": "page_1", "track_list": [{"length": "3:13", "title": "In the Tavern", "track_id": "track_1"}]}], "title": "In the Tavern", "work_id": "work_14130"}, {"npage": 1, "ntrack": 1, "page_list": [{"contributor": "Jos van Roy", "contributor_url": "https://www.classicalarchives.com/contributor/1869.html", "length": "1:56", "ntrack": 1, "page_id": "page_1", "track_list": [{"length": "1:56", "title": "Irrlichter", "track_id": "track_1"}]}], "title": "Irrlichter", "work_id": "work_14131"}, {"npage": 1, "ntrack": 1, "page_list": [{"contributor": "Jos van Roy", "contributor_url": "https://www.classicalarchives.com/contributor/1869.html", "length": "2:52", "ntrack": 1, "page_id": "page_1", "track_list": [{"length": "2:52", "title": "Serenade", "track_id": "track_1"}]}], "title": "Serenade", "work_id": "work_14132"}, {"npage": 1, "ntrack": 12, "page_list": [{"contributor": "Jos van Roy", "contributor_url": "https://www.classicalarchives.com/contributor/1869.html", "length": "27:41", "ntrack": 12, "page_id": "page_1", "track_list": [{"length": "2:11", "title": "Morgengruss", "track_id": "track_1"}, {"length": "3:41", "title": "Froher Wanderer", "track_id": "track_2"}, {"length": "1:59", "title": "Die M\u00fchle", "track_id": "track_3"}, {"length": "1:52", "title": "Kreuz am Wege", "track_id": "track_4"}, {"length": "1:53", "title": "Fernsicht", "track_id": "track_5"}, {"length": "2:28", "title": "Festlichkeit im Dorfe", "track_id": "track_6"}, {"length": "1:42", "title": "Nachmittags-Stille", "track_id": "track_7"}, {"length": "2:10", "title": "Waldkapelle", "track_id": "track_8"}, {"length": "2:44", "title": "Heimziehende Schnitter", "track_id": "track_9"}, {"length": "3:14", "title": "Im Wirtshaus", "track_id": "track_10"}, {"length": "2:03", "title": "Irrlichter", "track_id": "track_11"}, {"length": "1:44", "title": "Nachtgesang", "track_id": "track_12"}]}], "title": "Wanderbilder, Op.17", "work_id": "work_14133"}]}
