{"composer_id": "composer_3412", "composer_url": "https://www.classicalarchives.com/midi/composer/3412.html", "info": "(1822-1905); DEU", "name": "Franz Strauss", "ntrack": 3, "nwork": 2, "work_list": [{"npage": 2, "ntrack": 2, "page_list": [{"contributor": "Michel Brahhammer", "contributor_url": "https://www.classicalarchives.com/contributor/188.html", "length": "5:41", "ntrack": 1, "page_id": "page_1", "track_list": [{"length": "5:41", "title": "Nocturno f\u00fcr Horn in F und Pianoforte, Op.7", "track_id": "track_1"}]}, {"contributor": "Michel Brahhammer", "contributor_url": "https://www.classicalarchives.com/contributor/188.html", "length": "5:41", "ntrack": 1, "page_id": "page_2", "track_list": [{"length": "5:41", "title": "Nocturno f\u00fcr Horn in F und Pianoforte, Op.7", "track_id": "track_1"}]}], "title": "Nocturno f\u00fcr Horn in F und Pianoforte, Op.7", "work_id": "work_27801"}, {"npage": 1, "ntrack": 1, "page_list": [{"contributor": "Michel Brahhammer", "contributor_url": "https://www.classicalarchives.com/contributor/188.html", "length": "13:03", "ntrack": 1, "page_id": "page_1", "track_list": [{"length": "13:03", "title": "Thema und Variationen f\u00fcr Horn und Klavier, Op.13", "track_id": "track_1"}]}], "title": "Thema und Variationen f\u00fcr Horn und Klavier, Op.13", "work_id": "work_27802"}]}
