{"composer_id": "composer_607", "composer_url": "https://www.classicalarchives.com/midi/composer/607.html", "info": "(1985-); HKG", "name": "Frederick S. Gary", "ntrack": 1, "nwork": 1, "work_list": [{"npage": 1, "ntrack": 1, "page_list": [{"contributor": "anonymous contributor", "contributor_url": "https://www.classicalarchives.com/contributor/21729.html", "length": "2:57", "ntrack": 1, "page_id": "page_1", "track_list": [{"length": "2:57", "title": "Alto Recorder Duet in F#-", "track_id": "track_1"}]}], "title": "Alto Recorder Duet in F#-", "work_id": "work_10322"}]}
